odoo/addons/website_sale_loyalty_suggestion_wizard_multi_product/README.rst
odoo/addons/website_sale_loyalty_suggestion_wizard_multi_product/__init__.py
odoo/addons/website_sale_loyalty_suggestion_wizard_multi_product/__manifest__.py
odoo/addons/website_sale_loyalty_suggestion_wizard_multi_product/controllers/__init__.py
odoo/addons/website_sale_loyalty_suggestion_wizard_multi_product/controllers/main.py
odoo/addons/website_sale_loyalty_suggestion_wizard_multi_product/controllers/promotion_wizard.py
odoo/addons/website_sale_loyalty_suggestion_wizard_multi_product/i18n/it.po
odoo/addons/website_sale_loyalty_suggestion_wizard_multi_product/i18n/website_sale_loyalty_suggestion_wizard_multi_product.pot
odoo/addons/website_sale_loyalty_suggestion_wizard_multi_product/readme/CONTRIBUTORS.md
odoo/addons/website_sale_loyalty_suggestion_wizard_multi_product/readme/DESCRIPTION.md
odoo/addons/website_sale_loyalty_suggestion_wizard_multi_product/readme/USAGE.md
odoo/addons/website_sale_loyalty_suggestion_wizard_multi_product/static/description/icon.png
odoo/addons/website_sale_loyalty_suggestion_wizard_multi_product/static/description/index.html
odoo/addons/website_sale_loyalty_suggestion_wizard_multi_product/templates/wizard_templates.xml
odoo_addon_website_sale_loyalty_suggestion_wizard_multi_product-18.0.1.0.0.2.dist-info/METADATA
odoo_addon_website_sale_loyalty_suggestion_wizard_multi_product-18.0.1.0.0.2.dist-info/WHEEL
odoo_addon_website_sale_loyalty_suggestion_wizard_multi_product-18.0.1.0.0.2.dist-info/top_level.txt
odoo_addon_website_sale_loyalty_suggestion_wizard_multi_product-18.0.1.0.0.2.dist-info/RECORD
